storejson/__init__.py
storejson/core.py
storejson-0.1.1.dist-info/METADATA
storejson-0.1.1.dist-info/WHEEL
storejson-0.1.1.dist-info/RECORD
