Metadata-Version: 2.1
Name: storejson
Version: 0.1.1
Summary: Easiest way to Store JSON typed data using a Pydantic models and database-like structure.
License: MIT
Author: Izak57
Author-email: izak57k@gmail.com
Requires-Python: >=3.12,<4.0
Classifier: License :: OSI Approved :: MIT License
Classifier: Programming Language :: Python :: 3
Classifier: Programming Language :: Python :: 3.12
Requires-Dist: pydantic (>=2.8.2,<3.0.0)
